tile_image_grid/__init__.py
tile_image_grid/cli.py
tile_image_grid/image_reconstructor.py
tile_image_grid/image_splitter.py
tile_image_grid/processor.py
tile_image_grid-0.1.0.dist-info/LICENSE
tile_image_grid-0.1.0.dist-info/METADATA
tile_image_grid-0.1.0.dist-info/WHEEL
tile_image_grid-0.1.0.dist-info/entry_points.txt
tile_image_grid-0.1.0.dist-info/top_level.txt
tile_image_grid-0.1.0.dist-info/RECORD
