Metadata-Version: 2.2
Name: tile-image-grid
Version: 0.1.0
Summary: A command-line tool for splitting images into grids and reconstructing them back together
Home-page: https://github.com/passandscore/tile-image-grid
Author: passandscore
Author-email: jason.c.schwarz@gmail.com
License: MIT License
Project-URL: Homepage, https://github.com/passandscore/tile-image-grid
Project-URL: Repository, https://github.com/passandscore/tile-image-grid.git
Keywords: image,grid,split,reconstruct,tiles
Classifier: Development Status :: 3 - Alpha
Classifier: Intended Audience :: Developers
Classifier: License :: OSI Approved :: MIT License
Classifier: Programming Language :: Python :: 3
Classifier: Programming Language :: Python :: 3.7
Classifier: Programming Language :: Python :: 3.8
Classifier: Programming Language :: Python :: 3.9
Classifier: Programming Language :: Python :: 3.10
Classifier: Programming Language :: Python :: 3.11
Requires-Python: >=3.7
License-File: LICENSE
Requires-Dist: Pillow
Requires-Dist: click
Requires-Dist: torch
Dynamic: author-email
Dynamic: home-page
Dynamic: requires-python
